Metadata-Version: 2.1
Name: odoo-addon-account_fiscal_year_auto_create
Version: 18.0.1.0.0.2
Requires-Python: >=3.10
Requires-Dist: odoo-addon-account_fiscal_year==18.0.*
Requires-Dist: odoo==18.0.*
Summary: Automatically create new fiscal years, based on the datas of the last fiscal years
Home-page: https://github.com/OCA/account-financial-tools
License: AGPL-3
Author: GRAP,Odoo Community Association (OCA)
Author-email: support@odoo-community.org
Classifier: Programming Language :: Python
Classifier: Framework :: Odoo
Classifier: Framework :: Odoo :: 18.0
Classifier: License :: OSI Approved :: GNU Affero General Public License v3
